Metadata-Version: 1.1
Name: simple-passgen
Version: 0.1.0
Summary: Generate secure random character sequences, not inspired by XKCD
Home-page: https://github.com/JMurph2015/simple-passgen
Author: Joseph Murphy
Author-email: air.jmurph+simple-passgen@gmail.com
License: MIT
Platform: UNKNOWN
Classifier: Development Status :: 3 - Alpha
Classifier: Programming Language :: Python :: 2
Classifier: Programming Language :: Python :: 2.7
Classifier: Programming Language :: Python :: 3
Classifier: Programming Language :: Python :: 3.2
Classifier: Programming Language :: Python :: 3.3
Classifier: Programming Language :: Python :: 3.4
Classifier: Programming Language :: Python :: 3.5
Classifier: Environment :: Console
Classifier: Operating System :: OS Independent
Classifier: License :: OSI Approved :: GNU General Public License v3 or later (GPLv3+)
